MANIFEST.in
setup.py
RESOURCES/.suffix
RESOURCES/dummy
RESOURCES/eoeo.tst.py
RESOURCES/jobj.draft.py
RESOURCES/jobj.tst.py
RESOURCES/jobj2.draft.py
RESOURCES/length.tst.py
eobj/__init__.py
eobj/attr_fplfuncs.py
eobj/bin.py
eobj/eobj.py
eobj/ind.py
eobj/kastr.py
eobj/key_fplfuncs.py
eobj/kfplnd.py
eobj/orb.py
eobj/pathlist_funcs.py
eobj/primitive.py
eobj/st.py
eobj/wfsmat.py
eobj/wfsmat_const.py
eobj.egg-info/PKG-INFO
eobj.egg-info/SOURCES.txt
eobj.egg-info/dependency_links.txt
eobj.egg-info/entry_points.txt
eobj.egg-info/top_level.txt